client.py
venv2/bin/activate_this.py
hello_world_testcc-0.0.2.dist-info/LICENSE
hello_world_testcc-0.0.2.dist-info/METADATA
hello_world_testcc-0.0.2.dist-info/WHEEL
hello_world_testcc-0.0.2.dist-info/top_level.txt
hello_world_testcc-0.0.2.dist-info/RECORD
