Metadata-Version: 2.1
Name: hello-world-testcc
Version: 0.0.2
Summary: a Hello World Test Module
Author-email: chenchen <chen1233216@hotmail.com>
License: Apache License
Keywords: w3bstream
Requires-Python: >=3.7
License-File: LICENSE
Requires-Dist: requests
Requires-Dist: typeguard
